fastdkdc/__init__.py
fastdkdc-0.1.1.dist-info/WHEEL
fastdkdc-0.1.1.dist-info/entry_points.txt
fastdkdc-0.1.1.dist-info/METADATA
fastdkdc-0.1.1.dist-info/RECORD
