Metadata-Version: 2.3
Name: fastdkdc
Version: 0.1.1
Summary: fastdkdc
Author: Cody
Author-email: Cody <cody@dkdc.dev>
Requires-Python: >=3.13
